{
  "slug": "legal-trivia",
  "name": "Legal",
  "processedAt": "2026-05-24T20:43:43.614Z",
  "questions": [
    {
      "q": "Which amendment to the U.S. Constitution protects freedom of speech and the press?",
      "choices": [
        "Second Amendment",
        "First Amendment",
        "Fourth Amendment",
        "Fifth Amendment"
      ],
      "correct": 1,
      "difficulty": "easy"
    },
    {
      "q": "What is the term for the legal principle that courts should follow precedent established by earlier decisions?",
      "choices": [
        "Habeas corpus",
        "Pro bono",
        "Stare decisis",
        "Amicus curiae"
      ],
      "correct": 2,
      "difficulty": "easy"
    },
    {
      "q": "What title does the head of the U.S. Supreme Court hold?",
      "choices": [
        "President of the Court",
        "Chief Justice",
        "Senior Justice",
        "Lord Chief Judge"
      ],
      "correct": 1,
      "difficulty": "easy"
    },
    {
      "q": "Which Roman emperor commissioned the compilation of laws known as the Corpus Juris Civilis?",
      "choices": [
        "Augustus",
        "Marcus Aurelius",
        "Justinian I",
        "Diocletian"
      ],
      "correct": 2,
      "difficulty": "easy"
    },
    {
      "q": "What legal term describes the mental element or intent required to establish guilt in a crime?",
      "choices": [
        "Actus reus",
        "Mens rea",
        "Corpus delicti",
        "In camera"
      ],
      "correct": 1,
      "difficulty": "easy"
    },
    {
      "q": "Which branch of government has the power to interpret the constitutionality of laws?",
      "choices": [
        "Legislative branch",
        "Executive branch",
        "Judicial branch",
        "Administrative branch"
      ],
      "correct": 2,
      "difficulty": "easy"
    },
    {
      "q": "What is the legal term for rules enacted by a legislature?",
      "choices": [
        "Ordinances",
        "Statutes",
        "Bylaws",
        "Regulations"
      ],
      "correct": 1,
      "difficulty": "easy"
    },
    {
      "q": "Who was the legal scholar that first systematically collected and taught English common law as a unified system?",
      "choices": [
        "Edward Coke",
        "William Blackstone",
        "Thomas Hobbes",
        "John Locke"
      ],
      "correct": 1,
      "difficulty": "easy"
    },
    {
      "q": "Which Supreme Court case established the right to legal counsel for criminal defendants?",
      "choices": [
        "Marbury v. Madison",
        "Miranda v. Arizona",
        "Gideon v. Wainwright",
        "Plessy v. Ferguson"
      ],
      "correct": 2,
      "difficulty": "easy"
    },
    {
      "q": "What Supreme Court case ruled that separate but equal facilities are unconstitutional?",
      "choices": [
        "Plessy v. Ferguson",
        "Brown v. Board of Education",
        "Loving v. Virginia",
        "Korematsu v. United States"
      ],
      "correct": 1,
      "difficulty": "easy"
    },
    {
      "q": "Which legal philosopher famously defined law as 'the command of a sovereign, backed by the threat of a sanction'?",
      "choices": [
        "Thomas Aquinas",
        "John Austin",
        "Jeremy Bentham",
        "Hans Kelsen"
      ],
      "correct": 1,
      "difficulty": "easy"
    },
    {
      "q": "What is the legal term for a written court order requiring a person to appear before a judge?",
      "choices": [
        "Subpoena",
        "Summons",
        "Warrant",
        "Injunction"
      ],
      "correct": 0,
      "difficulty": "easy"
    },
    {
      "q": "Who was the first woman appointed as a Justice to the U.S. Supreme Court?",
      "choices": [
        "Ruth Bader Ginsburg",
        "Sandra Day O'Connor",
        "Sonia Sotomayor",
        "Elena Kagan"
      ],
      "correct": 1,
      "difficulty": "easy"
    },
    {
      "q": "Which Supreme Court case established the principle of judicial review of federal legislation?",
      "choices": [
        "McCulloch v. Maryland",
        "Marbury v. Madison",
        "Gibbons v. Ogden",
        "Fletcher v. Peck"
      ],
      "correct": 1,
      "difficulty": "easy"
    },
    {
      "q": "What is the legal term for a formal written accusation charging someone with a crime?",
      "choices": [
        "Indictment",
        "Complaint",
        "Arraignment",
        "Citation"
      ],
      "correct": 0,
      "difficulty": "easy"
    },
    {
      "q": "Which legal professional typically earns a Juris Doctor degree before practicing law?",
      "choices": [
        "Judge",
        "Lawyer",
        "Bailiff",
        "Paralegal"
      ],
      "correct": 1,
      "difficulty": "easy"
    },
    {
      "q": "What term describes the legal principle that a person cannot be punished twice for the same crime?",
      "choices": [
        "Mens rea",
        "Double jeopardy",
        "Habeas corpus",
        "Ex post facto"
      ],
      "correct": 1,
      "difficulty": "easy"
    },
    {
      "q": "Which Supreme Court case established Miranda rights for criminal suspects?",
      "choices": [
        "Terry v. Ohio",
        "Miranda v. Arizona",
        "Furman v. Georgia",
        "Atkins v. Virginia"
      ],
      "correct": 1,
      "difficulty": "easy"
    },
    {
      "q": "What is the legal term for a right that can be enforced against anyone in the world, not just specific parties?",
      "choices": [
        "Right in personam",
        "Right in rem",
        "Right in forma pauperis",
        "Right pro bono"
      ],
      "correct": 1,
      "difficulty": "easy"
    },
    {
      "q": "Which legal scholar argued that law should be understood as a 'system of rules' with primary and secondary rules?",
      "choices": [
        "Ronald Dworkin",
        "H.L.A. Hart",
        "Joseph Raz",
        "Lon Fuller"
      ],
      "correct": 1,
      "difficulty": "easy"
    },
    {
      "q": "Which legal professional is authorized to represent clients in court and provide legal advice?",
      "choices": [
        "Lawyer",
        "Bailiff",
        "Court clerk",
        "Paralegal"
      ],
      "correct": 0,
      "difficulty": "easy"
    },
    {
      "q": "What is the legal term for a civil wrong such as negligence or defamation?",
      "choices": [
        "Tort",
        "Felony",
        "Misdemeanor",
        "Contract breach"
      ],
      "correct": 0,
      "difficulty": "easy"
    },
    {
      "q": "In a lawsuit, what is the person who brings the case called?",
      "choices": [
        "Defendant",
        "Plaintiff",
        "Appellant",
        "Respondent"
      ],
      "correct": 1,
      "difficulty": "easy"
    },
    {
      "q": "Which U.S. Supreme Court decision established the right to legal counsel for defendants who cannot afford one?",
      "choices": [
        "Marbury v. Madison",
        "Gideon v. Wainwright",
        "Miranda v. Arizona",
        "Gibbons v. Ogden"
      ],
      "correct": 1,
      "difficulty": "easy"
    },
    {
      "q": "What does the legal doctrine 'stare decisis' require courts to do?",
      "choices": [
        "Dismiss cases without trial",
        "Follow precedent from previous decisions",
        "Appoint public defenders",
        "Publish all verdicts"
      ],
      "correct": 1,
      "difficulty": "easy"
    },
    {
      "q": "Which landmark Supreme Court case established the Miranda rights that police must read to suspects?",
      "choices": [
        "Brown v. Board of Education",
        "Roe v. Wade",
        "Miranda v. Arizona",
        "Plessy v. Ferguson"
      ],
      "correct": 2,
      "difficulty": "easy"
    },
    {
      "q": "What are the three essential elements required to form a valid contract under common law?",
      "choices": [
        "Offer, acceptance, and consideration",
        "Signature, notary, and witness",
        "Written form, verbal agreement, and payment",
        "Parties, location, and date"
      ],
      "correct": 0,
      "difficulty": "easy"
    },
    {
      "q": "Which legal professional works for the government to prosecute criminal cases on behalf of the state?",
      "choices": [
        "Defense attorney",
        "District attorney",
        "Judge",
        "Legal advisor"
      ],
      "correct": 1,
      "difficulty": "easy"
    },
    {
      "q": "What legal document issued by a court orders a person to appear before it?",
      "choices": [
        "Summons",
        "Warrant",
        "Subpoena",
        "Injunction"
      ],
      "correct": 0,
      "difficulty": "easy"
    },
    {
      "q": "Which branch of law primarily deals with crimes and their punishments?",
      "choices": [
        "Civil law",
        "Criminal law",
        "Administrative law",
        "International law"
      ],
      "correct": 1,
      "difficulty": "easy"
    },
    {
      "q": "What is the name of the legal code created in France in 1804 that became influential worldwide?",
      "choices": [
        "Justinian Code",
        "Napoleonic Code",
        "Germanic Code",
        "Byzantine Code"
      ],
      "correct": 1,
      "difficulty": "easy"
    },
    {
      "q": "In which century did William Blackstone first collect and teach common law as a coherent system?",
      "choices": [
        "15th century",
        "16th century",
        "18th century",
        "19th century"
      ],
      "correct": 2,
      "difficulty": "easy"
    },
    {
      "q": "What is judicially created law in common law systems called?",
      "choices": [
        "Statutory law",
        "Case law",
        "Regulatory law",
        "Ordinance"
      ],
      "correct": 1,
      "difficulty": "easy"
    },
    {
      "q": "Which U.S. Supreme Court case in 2015 legalized same-sex marriage nationwide?",
      "choices": [
        "United States v. Windsor",
        "Obergefell v. Hodges",
        "Loving v. Virginia",
        "Defense of Marriage Act"
      ],
      "correct": 1,
      "difficulty": "easy"
    },
    {
      "q": "What legal action challenges the constitutionality of a law or government action?",
      "choices": [
        "Tort claim",
        "Judicial review",
        "Appeal",
        "Arbitration"
      ],
      "correct": 1,
      "difficulty": "easy"
    },
    {
      "q": "Which legal professional would earn a Juris Doctor (JD) degree before practicing law?",
      "choices": [
        "Court reporter",
        "Lawyer",
        "Bailiff",
        "Paralegal"
      ],
      "correct": 1,
      "difficulty": "easy"
    },
    {
      "q": "What does the legal term 'plaintiff' refer to in a civil case?",
      "choices": [
        "The person being sued",
        "The judge presiding",
        "The party bringing the lawsuit",
        "The jury foreman"
      ],
      "correct": 2,
      "difficulty": "easy"
    },
    {
      "q": "Which legal system, based on written codes and statutes, is used in most of Europe and Latin America?",
      "choices": [
        "Common law",
        "Civil law",
        "Islamic law",
        "Customary law"
      ],
      "correct": 1,
      "difficulty": "easy"
    },
    {
      "q": "What legal term describes a court order prohibiting someone from doing a specific action?",
      "choices": [
        "Contempt",
        "Injunction",
        "Verdict",
        "Sentence"
      ],
      "correct": 1,
      "difficulty": "easy"
    },
    {
      "q": "In the ancient world, which civilization developed the Code of Hammurabi, one of the earliest known legal codes?",
      "choices": [
        "Ancient Egypt",
        "Ancient Mesopotamia",
        "Ancient Greece",
        "Ancient Rome"
      ],
      "correct": 1,
      "difficulty": "easy"
    },
    {
      "q": "What is the name of the 1215 English document that first limited the power of the monarchy?",
      "choices": [
        "Magna Carta",
        "Petition of Right",
        "English Bill of Rights",
        "Act of Settlement"
      ],
      "correct": 0,
      "difficulty": "easy"
    },
    {
      "q": "Which U.S. Supreme Court case established the principle of judicial review in 1803?",
      "choices": [
        "Marbury v. Madison",
        "McCulloch v. Maryland",
        "Gibbons v. Ogden",
        "Fletcher v. Peck"
      ],
      "correct": 0,
      "difficulty": "easy"
    },
    {
      "q": "What ancient Babylonian code, dating to around 1750 BC, is one of the oldest known written legal documents?",
      "choices": [
        "Code of Hammurabi",
        "Laws of Ur-Nammu",
        "Sumerian Edicts",
        "Hittite Code"
      ],
      "correct": 0,
      "difficulty": "easy"
    },
    {
      "q": "In 1932, which negligence case established the 'neighbor principle' in tort law?",
      "choices": [
        "Donoghue v. Stevenson",
        "Rylands v. Fletcher",
        "Palsgraf v. Long Island Railroad",
        "Hadley v. Baxendale"
      ],
      "correct": 0,
      "difficulty": "easy"
    },
    {
      "q": "Which famous legal code was created by Napoleon Bonaparte in 1804?",
      "choices": [
        "Napoleonic Code",
        "French Penal Code",
        "Justinian Code",
        "Code Civil Ancien"
      ],
      "correct": 0,
      "difficulty": "easy"
    },
    {
      "q": "What landmark 1966 U.S. Supreme Court decision established the right to remain silent and the right to an attorney?",
      "choices": [
        "Miranda v. Arizona",
        "Gideon v. Wainwright",
        "Duncan v. Louisiana",
        "Powell v. Alabama"
      ],
      "correct": 0,
      "difficulty": "easy"
    },
    {
      "q": "Which British legal philosopher wrote 'The Concept of Law' and defined law as a system of rules?",
      "choices": [
        "H. L. A. Hart",
        "John Austin",
        "Jeremy Bentham",
        "Lon Fuller"
      ],
      "correct": 0,
      "difficulty": "easy"
    },
    {
      "q": "In what year did the U.S. Supreme Court rule in Riley v. California that police need a warrant to search cell phones?",
      "choices": [
        "2014",
        "2011",
        "2015",
        "2013"
      ],
      "correct": 0,
      "difficulty": "easy"
    },
    {
      "q": "Which legal professional is responsible for writing judicial opinions that establish legal precedent?",
      "choices": [
        "Judge",
        "Lawyer",
        "Prosecutor",
        "Court clerk"
      ],
      "correct": 0,
      "difficulty": "easy"
    },
    {
      "q": "What is the Latin term for the guilty act or criminal conduct required to establish criminal liability?",
      "choices": [
        "Actus reus",
        "Mens rea",
        "Corpus delicti",
        "Nolo contendere"
      ],
      "correct": 0,
      "difficulty": "easy"
    },
    {
      "q": "Which civil rights lawyer successfully argued the Brown v. Board of Education case before the U.S. Supreme Court?",
      "choices": [
        "Thurgood Marshall",
        "Charles Hamilton Houston",
        "Malcolm X",
        "James Meredith"
      ],
      "correct": 0,
      "difficulty": "easy"
    },
    {
      "q": "What legal term describes a right that can be enforced against all people in the world, such as ownership of property?",
      "choices": [
        "Rights in rem",
        "Rights in personam",
        "Legal remedies",
        "Equitable rights"
      ],
      "correct": 0,
      "difficulty": "easy"
    },
    {
      "q": "In natural law theory, which philosopher argued that law should reflect universal laws of nature?",
      "choices": [
        "Immanuel Kant",
        "Thomas Hobbes",
        "Jean-Jacques Rousseau",
        "David Hume"
      ],
      "correct": 0,
      "difficulty": "easy"
    },
    {
      "q": "What is the term for a law imposed by an autocrat or ruler without approval from a legislature?",
      "choices": [
        "Decree",
        "Statute",
        "Ordinance",
        "Act"
      ],
      "correct": 0,
      "difficulty": "easy"
    },
    {
      "q": "Which branch of government in the United States creates the regulations that enforce legislative statutes?",
      "choices": [
        "Executive branch",
        "Legislative branch",
        "Judicial branch",
        "Independent agencies"
      ],
      "correct": 0,
      "difficulty": "easy"
    },
    {
      "q": "In the late 19th century, which country adopted a modified version of the German Civil Code to modernize its legal system?",
      "choices": [
        "Japan",
        "South Korea",
        "China",
        "Thailand"
      ],
      "correct": 0,
      "difficulty": "easy"
    },
    {
      "q": "What is the general term for a set of rules that are enforced by governmental or social institutions to regulate behavior?",
      "choices": [
        "Law",
        "Policy",
        "Custom",
        "Convention"
      ],
      "correct": 0,
      "difficulty": "easy"
    },
    {
      "q": "Which legal debate discusses whether a nation's constitution is written in a single document or based on unwritten traditions?",
      "choices": [
        "Codification debate",
        "Constitutional interpretation",
        "Separation of powers debate",
        "Federalism debate"
      ],
      "correct": 0,
      "difficulty": "easy"
    },
    {
      "q": "What academic field specifically asks the foundational question 'What is law?' and examines its nature and characteristics?",
      "choices": [
        "Analytic jurisprudence",
        "Legal history",
        "Comparative law",
        "Legal sociology"
      ],
      "correct": 0,
      "difficulty": "easy"
    },
    {
      "q": "What legal document, inscribed on a stone pillar, contained 282 laws and dates to approximately 1750 BC?",
      "choices": [
        "Code of Hammurabi",
        "Egyptian Book of the Dead",
        "Hittite Laws",
        "Sumerian Code"
      ],
      "correct": 0,
      "difficulty": "easy"
    },
    {
      "q": "What is the official title of the head of the United States Supreme Court?",
      "choices": [
        "Chief Justice",
        "President of the Court",
        "Judicial Chancellor",
        "Senior Justice"
      ],
      "correct": 0,
      "difficulty": "easy"
    },
    {
      "q": "Which U.S. constitutional amendment protects the right to free speech?",
      "choices": [
        "Second Amendment",
        "First Amendment",
        "Fifth Amendment",
        "Tenth Amendment"
      ],
      "correct": 1,
      "difficulty": "easy"
    },
    {
      "q": "In common law, what term describes the practice of following previous court decisions?",
      "choices": [
        "Stare decisis",
        "Habeas corpus",
        "Pro bono",
        "Amicus curiae"
      ],
      "correct": 0,
      "difficulty": "easy"
    },
    {
      "q": "What legal term refers to a written order commanding a person to appear in court?",
      "choices": [
        "Subpoena",
        "Summons",
        "Warrant",
        "Injunction"
      ],
      "correct": 1,
      "difficulty": "easy"
    },
    {
      "q": "Who was the first female justice appointed to the U.S. Supreme Court?",
      "choices": [
        "Ruth Bader Ginsburg",
        "Sandra Day O'Connor",
        "Sonia Sotomayor",
        "Elena Kagan"
      ],
      "correct": 1,
      "difficulty": "easy"
    },
    {
      "q": "Which ancient document, inscribed on a stone pillar, is considered one of the earliest written legal codes?",
      "choices": [
        "Code of Hammurabi",
        "Magna Carta",
        "Roman Twelve Tables",
        "Justinian's Digest"
      ],
      "correct": 0,
      "difficulty": "easy"
    },
    {
      "q": "What is the power of courts to declare laws unconstitutional called?",
      "choices": [
        "Legislative review",
        "Executive override",
        "Judicial review",
        "Constitutional veto"
      ],
      "correct": 2,
      "difficulty": "easy"
    },
    {
      "q": "In legal terminology, what is the person who initiates a lawsuit called?",
      "choices": [
        "Defendant",
        "Plaintiff",
        "Appellant",
        "Petitioner"
      ],
      "correct": 1,
      "difficulty": "easy"
    },
    {
      "q": "What legal term describes rules or laws enacted by a legislature?",
      "choices": [
        "Statute",
        "Precedent",
        "Ordinance",
        "Regulation"
      ],
      "correct": 0,
      "difficulty": "easy"
    },
    {
      "q": "In 2015, the U.S. Supreme Court ruled that which right must be recognized across all states?",
      "choices": [
        "Voting regardless of felony conviction",
        "Same-sex marriage",
        "Right to bear arms without restriction",
        "Universal healthcare"
      ],
      "correct": 1,
      "difficulty": "easy"
    },
    {
      "q": "In H.L.A. Hart's legal positivism, what does he identify as the fundamental distinction between primary and secondary rules?",
      "choices": [
        "Primary rules govern conduct; secondary rules govern the creation and modification of primary rules",
        "Primary rules apply only to citizens; secondary rules apply to government officials",
        "Primary rules are written; secondary rules are customary",
        "Primary rules establish courts; secondary rules establish legislatures"
      ],
      "correct": 0,
      "difficulty": "hard"
    },
    {
      "q": "Which 1963 U.S. Supreme Court decision established the constitutional right to counsel in criminal cases at state and federal levels?",
      "choices": [
        "Powell v. Alabama",
        "Gideon v. Wainwright",
        "Furman v. Georgia",
        "Duncan v. Louisiana"
      ],
      "correct": 1,
      "difficulty": "hard"
    },
    {
      "q": "In the Law Merchant tradition of medieval Europe, what legal mechanism allowed disputes among merchants to be resolved through standardized commercial practices across different jurisdictions?",
      "choices": [
        "Guild arbitration by trade associations",
        "Royal intervention through appointed judges",
        "Written statutes enacted by each city-state",
        "Canon law courts presided over by bishops"
      ],
      "correct": 0,
      "difficulty": "hard"
    },
    {
      "q": "Ronald Dworkin's theory of law as 'interpretive concept' proposes that legal interpretation must aim toward which overarching goal?",
      "choices": [
        "Predictability of judicial outcomes",
        "Maximizing legislative intent",
        "Achieving the best moral and political justification",
        "Maintaining internal logical consistency"
      ],
      "correct": 2,
      "difficulty": "hard"
    },
    {
      "q": "In Islamic jurisprudence, Qiyas refers to which method of legal reasoning?",
      "choices": [
        "Consensus among legal scholars on a matter not explicitly covered by scripture",
        "Reasoning by analogy from established precedents in the Quran and Hadith",
        "The literal textual interpretation of religious sources",
        "Individual scholarly judgment in cases of public interest"
      ],
      "correct": 1,
      "difficulty": "hard"
    },
    {
      "q": "Which 2014 U.S. Supreme Court decision held that police must obtain a warrant before searching the contents of a mobile device incident to arrest?",
      "choices": [
        "United States v. Jones",
        "Riley v. California",
        "Kyllo v. United States",
        "Florida v. Harris"
      ],
      "correct": 1,
      "difficulty": "hard"
    },
    {
      "q": "According to John Austin's command theory of law, what essential characteristic must accompany a sovereign's command for it to constitute legal obligation?",
      "choices": [
        "Ratification by a deliberative assembly",
        "Adherence to natural law principles",
        "A threat of sanction for disobedience",
        "Public announcement in official records"
      ],
      "correct": 2,
      "difficulty": "hard"
    },
    {
      "q": "In tort law, which case established the modern principle that a duty of care is owed to persons who are foreseeably affected by one's conduct, not merely to those in direct contractual privity?",
      "choices": [
        "Palsgraf v. Long Island Railroad Co.",
        "Donoghue v. Stevenson",
        "Rylands v. Fletcher",
        "Winterbottom v. Wright"
      ],
      "correct": 1,
      "difficulty": "hard"
    },
    {
      "q": "Under common law contract doctrine, what term describes the act of unconditionally agreeing to all material terms of an offer without introducing new conditions?",
      "choices": [
        "Consideration",
        "Offer",
        "Acceptance",
        "Mutual assent"
      ],
      "correct": 2,
      "difficulty": "hard"
    },
    {
      "q": "Which natural law theorist argued that law reflects immutable principles derived from human reason and universal nature, rather than mere sovereign command?",
      "choices": [
        "Thomas Hobbes",
        "Immanuel Kant",
        "Jeremy Bentham",
        "David Hume"
      ],
      "correct": 1,
      "difficulty": "hard"
    },
    {
      "q": "In 1944, which U.S. Supreme Court case upheld the constitutionality of Japanese internment during World War II, establishing a standard of heightened judicial scrutiny for classifications based on race?",
      "choices": [
        "Lochner v. New York",
        "Korematsu v. United States",
        "Plessy v. Ferguson",
        "Hirabayashi v. United States"
      ],
      "correct": 1,
      "difficulty": "hard"
    },
    {
      "q": "What legal doctrine, articulated in Marbury v. Madison, grants federal courts the authority to strike down legislation they deem unconstitutional?",
      "choices": [
        "Separation of powers",
        "Judicial review",
        "Supremacy Clause application",
        "Federalism"
      ],
      "correct": 1,
      "difficulty": "hard"
    },
    {
      "q": "Which Sumerian legal code, attributed to King Ur-Nammu, is considered one of the earliest written legal systems in recorded history?",
      "choices": [
        "Code of Hammurabi",
        "Code of Ur-Nammu",
        "Lipit-Ishtar Law Code",
        "Eshunna Code"
      ],
      "correct": 1,
      "difficulty": "hard"
    },
    {
      "q": "In the doctrine of natural law, what concept refers to the notion that law derives moral force from alignment with transcendent principles of justice rather than legislative will alone?",
      "choices": [
        "Legal positivism",
        "Legal realism",
        "Natural law legitimacy",
        "Rule of law"
      ],
      "correct": 2,
      "difficulty": "hard"
    },
    {
      "q": "Which 2015 U.S. Supreme Court decision held that state constitutional bans on same-sex marriage violated the Fourteenth Amendment's guarantees of liberty and equal protection?",
      "choices": [
        "United States v. Windsor",
        "Obergefell v. Hodges",
        "Loving v. Virginia",
        "Lawrence v. Texas"
      ],
      "correct": 1,
      "difficulty": "hard"
    },
    {
      "q": "In medieval English law, which 1215 document forced King John to acknowledge limitations on royal prerogative and establish protections for feudal and property rights?",
      "choices": [
        "Constitutio Criminalis Carolina",
        "Magna Carta",
        "Statute of Westminster",
        "Bill of Rights"
      ],
      "correct": 1,
      "difficulty": "hard"
    },
    {
      "q": "Which civil rights attorney successfully argued on behalf of the appellants in Brown v. Board of Education, challenging the constitutionality of segregation in public schools?",
      "choices": [
        "James Marshall",
        "Thurgood Marshall",
        "John Marshall Harlan",
        "Charles Hamilton Houston"
      ],
      "correct": 1,
      "difficulty": "hard"
    },
    {
      "q": "In jurisprudence, what term describes the branch of legal theory concerned with prescriptive questions about how law ought to be structured and what values it should advance?",
      "choices": [
        "Descriptive jurisprudence",
        "Analytic jurisprudence",
        "Normative jurisprudence",
        "Comparative jurisprudence"
      ],
      "correct": 2,
      "difficulty": "hard"
    },
    {
      "q": "Which doctrine in tort law holds that a plaintiff is barred from recovery if their own negligent conduct substantially contributed to their injury, even if the defendant was also negligent?",
      "choices": [
        "Comparative negligence",
        "Contributory negligence",
        "Assumption of risk",
        "Mitigation of damages"
      ],
      "correct": 1,
      "difficulty": "hard"
    },
    {
      "q": "In contract law, what term describes the requirement that a promisor receive something of value in exchange for their promise in order for a contract to be enforceable?",
      "choices": [
        "Offer",
        "Consideration",
        "Warranty",
        "Covenant"
      ],
      "correct": 1,
      "difficulty": "hard"
    },
    {
      "q": "In Hart's legal philosophy, what term describes the foundational rules that grant power to create other legal rules?",
      "choices": [
        "Primary rules",
        "Secondary rules",
        "Enabling rules",
        "Sovereign rules"
      ],
      "correct": 1,
      "difficulty": "hard"
    },
    {
      "q": "Which medieval European legal framework, originating in merchant practices, formed the basis for modern commercial law?",
      "choices": [
        "Lex Talionis",
        "Lex Mercatoria",
        "Lex Salica",
        "Lex Romana"
      ],
      "correct": 1,
      "difficulty": "hard"
    },
    {
      "q": "What legal principle, established in Marbury v. Madison, grants courts the power to strike down unconstitutional legislation?",
      "choices": [
        "Stare decisis",
        "Judicial review",
        "Certiorari",
        "Habeas corpus"
      ],
      "correct": 1,
      "difficulty": "hard"
    },
    {
      "q": "In civil law systems, what term describes laws enacted by the legislature as the primary source of legal authority?",
      "choices": [
        "Customary law",
        "Statutory law",
        "Case law",
        "Jurisprudence constante"
      ],
      "correct": 1,
      "difficulty": "hard"
    },
    {
      "q": "Which fiduciary relationship requires the highest duty of care, specifically prohibiting self-dealing without full disclosure?",
      "choices": [
        "Principal-agent relationship",
        "Trustee-beneficiary relationship",
        "Mortgagor-mortgagee relationship",
        "Vendor-vendee relationship"
      ],
      "correct": 1,
      "difficulty": "hard"
    },
    {
      "q": "What doctrine, articulated by Ronald Dworkin, posits that judges discover law through interpretive integrity rather than creating it?",
      "choices": [
        "Legal realism",
        "Interpretivism",
        "Positivism",
        "Naturalism"
      ],
      "correct": 1,
      "difficulty": "hard"
    },
    {
      "q": "In the Ottoman legal system, what was the Mecelle primarily designed to accomplish?",
      "choices": [
        "Codify Sharia law for administrative uniformity",
        "Establish parliamentary procedures",
        "Regulate merchant guilds",
        "Determine criminal sentencing"
      ],
      "correct": 0,
      "difficulty": "hard"
    },
    {
      "q": "Which Supreme Court decision established that the Fifth Amendment's self-incrimination clause applies to custodial interrogation?",
      "choices": [
        "Gideon v. Wainwright",
        "Miranda v. Arizona",
        "Escobedo v. Illinois",
        "Malloy v. Hogan"
      ],
      "correct": 1,
      "difficulty": "hard"
    },
    {
      "q": "What is the legal term for a real property interest that binds successive owners and cannot be removed by a subsequent purchaser?",
      "choices": [
        "Covenant running with the land",
        "Equitable servitude",
        "Easement appurtenant",
        "Restrictive covenant"
      ],
      "correct": 0,
      "difficulty": "hard"
    },
    {
      "q": "In contract law, what doctrine excuses performance when an unforeseen event makes performance impossible or impracticable?",
      "choices": [
        "Force majeure",
        "Impossibility or impracticability",
        "Frustration of purpose",
        "Material breach"
      ],
      "correct": 1,
      "difficulty": "hard"
    },
    {
      "q": "Which Scottish legal theorist's works on jurisprudence influenced the development of modern analytical legal philosophy?",
      "choices": [
        "David Hume",
        "John Austin",
        "Francis Hutcheson",
        "Henry Home"
      ],
      "correct": 1,
      "difficulty": "hard"
    },
    {
      "q": "What constitutional doctrine permits Congress to regulate interstate commerce, including activities substantially affecting interstate commerce?",
      "choices": [
        "Dormant Commerce Clause",
        "Substantial Effects Test",
        "Necessary and Proper Clause",
        "Commerce Clause Power"
      ],
      "correct": 1,
      "difficulty": "hard"
    },
    {
      "q": "In admiralty law, what principle determines liability for maritime collisions between vessels of equal fault?",
      "choices": [
        "Rule of comparative negligence",
        "Rule of divided damages",
        "Last clear chance doctrine",
        "Doctrine of assumption of risk"
      ],
      "correct": 1,
      "difficulty": "hard"
    },
    {
      "q": "Which legal concept describes the unenforceable nature of agreements that violate fundamental public policy?",
      "choices": [
        "Void ab initio",
        "Voidable contract",
        "Unconscionability",
        "Illegal consideration"
      ],
      "correct": 0,
      "difficulty": "hard"
    },
    {
      "q": "What does the legal maxim 'nolo contendere' permit a defendant to do in criminal proceedings?",
      "choices": [
        "Plead guilty without admitting guilt",
        "Withdraw a guilty plea",
        "Request a jury trial waiver",
        "Challenge prosecutorial discretion"
      ],
      "correct": 0,
      "difficulty": "hard"
    },
    {
      "q": "In securities law, what doctrine holds corporate officers and directors liable for short-swing profits on company stock?",
      "choices": [
        "Section 16(b) short-swing profit rule",
        "Insider trading doctrine",
        "Beneficial ownership rule",
        "Control person liability"
      ],
      "correct": 0,
      "difficulty": "hard"
    },
    {
      "q": "Which legal framework governs the assignment and delegation of contractual rights and duties to third parties?",
      "choices": [
        "Novation doctrine",
        "Third-party beneficiary doctrine",
        "Assignment and delegation rules",
        "Privity of contract"
      ],
      "correct": 2,
      "difficulty": "hard"
    },
    {
      "q": "In constitutional law, what term describes a restriction on government power derived from the separation of powers principle?",
      "choices": [
        "Enumerated powers doctrine",
        "Police power limitation",
        "Inherent structural constraint",
        "Categorical immunity"
      ],
      "correct": 2,
      "difficulty": "hard"
    },
    {
      "q": "What is the primary distinction between tort law's 'strict liability' and 'negligence-based' liability standards?",
      "choices": [
        "Strict liability requires proof of intent; negligence does not",
        "Strict liability imposes liability without fault; negligence requires breach of duty",
        "Negligence is only for contractual relationships",
        "Strict liability applies only to property damage"
      ],
      "correct": 1,
      "difficulty": "hard"
    },
    {
      "q": "Which Anglo-American legal maxim prohibits a party from profiting from their own wrongdoing or breach of duty?",
      "choices": [
        "Estoppel principle",
        "Clean hands doctrine",
        "Unclean hands doctrine",
        "In pari delicto"
      ],
      "correct": 2,
      "difficulty": "hard"
    },
    {
      "q": "In H.L.A. Hart's legal positivism, what did he identify as the foundational element that distinguishes a legal system from mere coercion?",
      "choices": [
        "The presence of secondary rules governing the creation and application of primary rules",
        "The existence of a sovereign backed by force",
        "The universal consent of all members of society",
        "The alignment of law with natural law principles"
      ],
      "correct": 0,
      "difficulty": "hard"
    },
    {
      "q": "Which Roman legal codification, commissioned by Emperor Justinian I in the 6th century, synthesized centuries of imperial legislation and jurisprudence?",
      "choices": [
        "Lex Romana Visigothorum",
        "Corpus Juris Civilis",
        "Edictum Perpetuum",
        "Codex Theodosianus"
      ],
      "correct": 1,
      "difficulty": "hard"
    },
    {
      "q": "In tort law, the principle of 'duty of care' was formally established in the neighbor principle as articulated in which landmark 1932 case?",
      "choices": [
        "Bolton v. Stone",
        "Rylands v. Fletcher",
        "Donoghue v. Stevenson",
        "Hedley Byrne & Co v. Heller & Partners"
      ],
      "correct": 2,
      "difficulty": "hard"
    },
    {
      "q": "What is the Latin term for the doctrine that courts should respect precedent and adhere to earlier judicial decisions?",
      "choices": [
        "Ratio decidendi",
        "Stare decisis",
        "Obiter dictum",
        "Mens rea"
      ],
      "correct": 1,
      "difficulty": "hard"
    },
    {
      "q": "Which legal theorist in the 19th century defined law as 'the command of a sovereign, backed by the threat of a sanction'?",
      "choices": [
        "Jeremy Bentham",
        "John Austin",
        "Frederick Pollock",
        "Oliver Wendell Holmes Jr."
      ],
      "correct": 1,
      "difficulty": "hard"
    },
    {
      "q": "The Napoleonic Code of 1804 served as the foundation for civil law systems across Europe. Which two legal traditions did it primarily synthesize?",
      "choices": [
        "Germanic custom and Roman law",
        "Canon law and English common law",
        "Roman law and French customary law",
        "Islamic law and continental European statutes"
      ],
      "correct": 2,
      "difficulty": "hard"
    },
    {
      "q": "In the landmark contract law case involving the Carbolic Smoke Ball Company, what was the central legal issue regarding the advertisement?",
      "choices": [
        "Whether false advertising constituted actionable misrepresentation",
        "Whether an advertisement could constitute a binding contractual offer",
        "Whether the company had adequate product liability insurance",
        "Whether consumer protection statutes applied retroactively"
      ],
      "correct": 1,
      "difficulty": "hard"
    },
    {
      "q": "Thomas Aquinas argued that law must be promulgated for the common good. Which concept did he emphasize as essential to the definition of law?",
      "choices": [
        "Divine sanction and eternal punishment",
        "Rational ordering directed toward the common good",
        "Absolute obedience to monarchical authority",
        "Perfect consonance with natural law"
      ],
      "correct": 1,
      "difficulty": "hard"
    },
    {
      "q": "The Code of Hammurabi, compiled during the reign of Babylonian King Hammurabi around 1760 BC, represented a landmark achievement primarily because it was:",
      "choices": [
        "The first written legal code to establish trial by jury",
        "A comprehensive written code that unified disparate regional laws",
        "The first code to abolish slavery",
        "An early attempt at international treaty law"
      ],
      "correct": 1,
      "difficulty": "hard"
    },
    {
      "q": "Which comprehensive civil code, adopted in Germany in 1900 and enacted in 1901, was the first unified civil law code of a major European power?",
      "choices": [
        "Preussisches Allgemeines Landrecht",
        "Bürgerliches Gesetzbuch",
        "Deutsches Strafgesetzbuch",
        "Konstitutionstag Kodex"
      ],
      "correct": 1,
      "difficulty": "hard"
    },
    {
      "q": "In the 1829 North Carolina case State v. Mann, the court ruled that a master had the legal right to use physical punishment against enslaved people. This decision exemplified which aspect of American legal history?",
      "choices": [
        "The expansion of habeas corpus protections",
        "The judicial enforcement of property rights in enslaved persons",
        "The establishment of criminal liability for assault",
        "The recognition of constitutional due process"
      ],
      "correct": 1,
      "difficulty": "hard"
    },
    {
      "q": "Which U.S. Supreme Court decision in 1963 established the constitutional right to counsel for criminal defendants unable to afford an attorney?",
      "choices": [
        "Miranda v. Arizona",
        "Gideon v. Wainwright",
        "Duncan v. Louisiana",
        "Powell v. Alabama"
      ],
      "correct": 1,
      "difficulty": "hard"
    },
    {
      "q": "The 2014 U.S. Supreme Court decision Riley v. California addressed the constitutional permissibility of warrantless searches in which context?",
      "choices": [
        "Searches of vehicles at border crossings",
        "Searches of mobile phones incident to arrest",
        "Searches of email accounts with consent",
        "Searches of financial records with subpoena"
      ],
      "correct": 1,
      "difficulty": "hard"
    },
    {
      "q": "Sir Edward Coke famously characterized law using what phrase, suggesting its connection to principles of justice and equity?",
      "choices": [
        "'The guardian of property'",
        "'The art of justice'",
        "'The voice of reason'",
        "'The foundation of order'"
      ],
      "correct": 1,
      "difficulty": "hard"
    },
    {
      "q": "Under King Henry II of England in the 12th century, the development of what judicial institution laid the groundwork for the English common law system?",
      "choices": [
        "Circuit courts staffed by itinerant justices",
        "Independent magistrate courts",
        "Ecclesiastical courts with secular oversight",
        "Parliamentary legislative committees"
      ],
      "correct": 0,
      "difficulty": "hard"
    },
    {
      "q": "In classical Greek legal thought, which three distinct categories of law did Athenian philosophers distinguish—divine law, human decree, and custom?",
      "choices": [
        "Thémis, nomos, and díkē",
        "Nomoi, edikta, and ethoi",
        "Theos, anthropos, and sunetheia",
        "Dike, themis, and psyche"
      ],
      "correct": 0,
      "difficulty": "hard"
    },
    {
      "q": "Scholarly debate concerning the Theodosian Code centers on which fundamental historical question about early medieval Europe?",
      "choices": [
        "Whether it was successfully enforced in all Roman provinces",
        "The extent to which it shaped the fusion of Roman law with Germanic custom",
        "Its influence on Islamic legal tradition",
        "The role of the Pope in its codification"
      ],
      "correct": 1,
      "difficulty": "hard"
    },
    {
      "q": "What is the distinction in legal reasoning between 'ratio decidendi' and 'obiter dictum' in common law jurisprudence?",
      "choices": [
        "Ratio decidendi applies only in criminal cases; obiter dictum applies in civil cases",
        "Ratio decidendi is the binding reason for the decision; obiter dictum is incidental commentary",
        "Ratio decidendi is written opinion; obiter dictum is oral argument",
        "Ratio decidendi creates precedent; obiter dictum is never cited"
      ],
      "correct": 1,
      "difficulty": "hard"
    },
    {
      "q": "In legal pluralism, what is the primary scholarly concern regarding the interaction between canon law and English common law during the medieval period?",
      "choices": [
        "Whether canon law courts had superior jurisdiction",
        "The mechanisms and extent of substantive and procedural influence between the two systems",
        "Whether canon law was ever fully adopted in England",
        "The role of the monarchy in suppressing canon law"
      ],
      "correct": 1,
      "difficulty": "hard"
    },
    {
      "q": "Which legal professional role, as distinguished from judges and attorneys, holds the responsibility for prosecuting criminal cases on behalf of the state at the trial level?",
      "choices": [
        "Public defender",
        "District attorney or prosecutor",
        "Solicitor general",
        "Attorney general"
      ],
      "correct": 1,
      "difficulty": "hard"
    },
    {
      "q": "In jurisprudence, which scholar's 'positivist' theory defined law as a 'system of rules' separated from morality?",
      "choices": [
        "John Austin",
        "H. L. A. Hart",
        "Ronald Dworkin",
        "Lon Fuller"
      ],
      "correct": 1,
      "difficulty": "hard"
    },
    {
      "q": "Which Roman Emperor commissioned the comprehensive legal compilation known as the Corpus Juris Civilis in the 6th century?",
      "choices": [
        "Augustus",
        "Justinian I",
        "Diocletian",
        "Constantine"
      ],
      "correct": 1,
      "difficulty": "hard"
    },
    {
      "q": "In tort law, the landmark case establishing that manufacturers owe a duty of care to consumers involved a defective product of what type?",
      "choices": [
        "A faulty carriage wheel",
        "Contaminated ginger beer",
        "Defective machinery",
        "Poisoned food at a restaurant"
      ],
      "correct": 1,
      "difficulty": "hard"
    },
    {
      "q": "Which U.S. Supreme Court decision in 2014 held that police cannot search a mobile phone without a warrant during an arrest?",
      "choices": [
        "Carpenter v. United States",
        "Riley v. California",
        "United States v. Jones",
        "Kyllo v. United States"
      ],
      "correct": 1,
      "difficulty": "hard"
    },
    {
      "q": "In medieval England, which principle of canon law regarding the secrecy of confessions influenced the development of attorney-client privilege in common law?",
      "choices": [
        "Sacramentum fidei",
        "Sigillum confessionis",
        "Privilegium clericale",
        "Beneficium competentiae"
      ],
      "correct": 1,
      "difficulty": "hard"
    },
    {
      "q": "Which fiduciary relationship imposes the strictest duty of loyalty, requiring the fiduciary to place the beneficiary's interests above their own?",
      "choices": [
        "Principal-agent relationship",
        "Trustee-beneficiary relationship",
        "Bailee-bailor relationship",
        "Director-shareholder relationship"
      ],
      "correct": 1,
      "difficulty": "hard"
    },
    {
      "q": "The 'actus reus' element in criminal law refers to which component of criminal liability?",
      "choices": [
        "The defendant's guilty mind or intent",
        "The defendant's external guilty act or conduct",
        "The defendant's motive for committing the crime",
        "The defendant's prior criminal history"
      ],
      "correct": 1,
      "difficulty": "hard"
    },
    {
      "q": "Which legal doctrine allows courts to overturn legislation deemed inconsistent with a nation's constitution?",
      "choices": [
        "Stare decisis",
        "Judicial review",
        "Separation of powers",
        "Supremacy clause"
      ],
      "correct": 1,
      "difficulty": "hard"
    },
    {
      "q": "In the late 19th century, which European legal system did Japan's Meiji government primarily model its civil code upon?",
      "choices": [
        "The French Napoleonic Code",
        "The German Civil Code",
        "The Austrian legal system",
        "The Italian Codice Civile"
      ],
      "correct": 1,
      "difficulty": "hard"
    },
    {
      "q": "Which principle of contract law holds that consideration must move from the promisee to the promisor, establishing mutual exchange?",
      "choices": [
        "Doctrine of estoppel",
        "Privity of contract",
        "Sufficiency of consideration",
        "Bargain theory of consideration"
      ],
      "correct": 3,
      "difficulty": "hard"
    },
    {
      "q": "In contract law, what term describes something of value that each party to a contract must exchange?",
      "choices": [
        "Consideration",
        "Covenant",
        "Indemnity",
        "Estoppel"
      ],
      "correct": 0,
      "difficulty": "medium"
    },
    {
      "q": "Which 1803 Supreme Court case established the principle of judicial review?",
      "choices": [
        "McCulloch v. Maryland",
        "Marbury v. Madison",
        "Gibbons v. Ogden",
        "Fletcher v. Peck"
      ],
      "correct": 1,
      "difficulty": "medium"
    },
    {
      "q": "What is the legal term for a court order requiring a person to appear and testify under oath?",
      "choices": [
        "Writ of habeas corpus",
        "Subpoena",
        "Injunction",
        "Contempt"
      ],
      "correct": 1,
      "difficulty": "medium"
    },
    {
      "q": "In 1964, which landmark Supreme Court case guaranteed the right to counsel in criminal cases?",
      "choices": [
        "Miranda v. Arizona",
        "Gideon v. Wainwright",
        "Duncan v. Louisiana",
        "Furman v. Georgia"
      ],
      "correct": 1,
      "difficulty": "medium"
    },
    {
      "q": "Which legal doctrine allows a previous court decision to bind future courts in similar cases?",
      "choices": [
        "Res judicata",
        "Stare decisis",
        "Pro bono",
        "Amicus curiae"
      ],
      "correct": 1,
      "difficulty": "medium"
    },
    {
      "q": "What term describes laws enacted by a legislative body?",
      "choices": [
        "Ordinance",
        "Statute",
        "Regulation",
        "Bylaw"
      ],
      "correct": 1,
      "difficulty": "medium"
    },
    {
      "q": "In 1954, Thurgood Marshall argued which Supreme Court case that struck down school segregation?",
      "choices": [
        "Plessy v. Ferguson",
        "Loving v. Virginia",
        "Brown v. Board of Education",
        "Green v. County School Board"
      ],
      "correct": 2,
      "difficulty": "medium"
    },
    {
      "q": "Which U.S. Constitutional amendment protects freedom of speech and religion?",
      "choices": [
        "Eighth Amendment",
        "First Amendment",
        "Fifth Amendment",
        "Fourteenth Amendment"
      ],
      "correct": 1,
      "difficulty": "medium"
    },
    {
      "q": "What legal term refers to a false statement made with knowledge of its falsity that damages someone's reputation?",
      "choices": [
        "Fraud",
        "Libel",
        "Battery",
        "Negligence"
      ],
      "correct": 1,
      "difficulty": "medium"
    },
    {
      "q": "Which ancient legal code, created around 1754 BC, is among the oldest known written law systems?",
      "choices": [
        "Code of Hammurabi",
        "Justinian Code",
        "Laws of Eshnunna",
        "Ur-Nammu Code"
      ],
      "correct": 0,
      "difficulty": "medium"
    },
    {
      "q": "In criminal procedure, what is the name of the initial appearance where defendants are informed of charges?",
      "choices": [
        "Trial",
        "Arraignment",
        "Preliminary hearing",
        "Grand jury indictment"
      ],
      "correct": 1,
      "difficulty": "medium"
    },
    {
      "q": "Which Supreme Court case in 2015 legalized same-sex marriage nationwide?",
      "choices": [
        "United States v. Windsor",
        "Hollingsworth v. Perry",
        "Obergefell v. Hodges",
        "Lawrence v. Texas"
      ],
      "correct": 2,
      "difficulty": "medium"
    },
    {
      "q": "What legal principle prevents a person from being tried twice for the same crime?",
      "choices": [
        "Habeas corpus",
        "Double jeopardy",
        "Miranda rights",
        "Presumption of innocence"
      ],
      "correct": 1,
      "difficulty": "medium"
    },
    {
      "q": "Which judge famously defined law as 'the prophecies of what the courts will do in fact'?",
      "choices": [
        "Benjamin Cardozo",
        "Oliver Wendell Holmes",
        "John Marshall",
        "Earl Warren"
      ],
      "correct": 1,
      "difficulty": "medium"
    },
    {
      "q": "In tort law, what term describes the legal responsibility to avoid causing harm through negligent actions?",
      "choices": [
        "Duty of care",
        "Assumption of risk",
        "Comparative negligence",
        "Strict liability"
      ],
      "correct": 0,
      "difficulty": "medium"
    },
    {
      "q": "What is the legal term for an agreement between two or more parties that is enforceable by law?",
      "choices": [
        "Covenant",
        "Contract",
        "Settlement",
        "Accord"
      ],
      "correct": 1,
      "difficulty": "medium"
    },
    {
      "q": "Which branch of government interprets the constitutionality of laws?",
      "choices": [
        "Legislative branch",
        "Executive branch",
        "Judicial branch",
        "Administrative branch"
      ],
      "correct": 2,
      "difficulty": "medium"
    },
    {
      "q": "In 2018, which Supreme Court case established privacy rights for digital cell phone searches?",
      "choices": [
        "Florida v. Harris",
        "Riley v. California",
        "Missouri v. McNeely",
        "Kentucky v. King"
      ],
      "correct": 1,
      "difficulty": "medium"
    },
    {
      "q": "What legal doctrine holds that statements made in court proceedings cannot be used as grounds for defamation?",
      "choices": [
        "Qualified privilege",
        "Absolute privilege",
        "Opinion privilege",
        "Public concern privilege"
      ],
      "correct": 1,
      "difficulty": "medium"
    },
    {
      "q": "Which legal professional represents the state in prosecuting criminal offenses?",
      "choices": [
        "Public defender",
        "District attorney",
        "Solicitor general",
        "Defense counsel"
      ],
      "correct": 1,
      "difficulty": "medium"
    },
    {
      "q": "In contract law, what term describes a situation where one party's promise is exchanged for another party's promise or performance?",
      "choices": [
        "Consideration",
        "Estoppel",
        "Novation",
        "Rescission"
      ],
      "correct": 0,
      "difficulty": "medium"
    },
    {
      "q": "Which legal doctrine allows a court to refuse to enforce a law it deems unconstitutional?",
      "choices": [
        "Separation of powers",
        "Judicial review",
        "Substantive due process",
        "Dormant commerce clause"
      ],
      "correct": 1,
      "difficulty": "medium"
    },
    {
      "q": "What is the legal term for the mental element or intent required to establish criminal liability?",
      "choices": [
        "Actus reus",
        "Mens rea",
        "Nolo contendere",
        "Corpus delicti"
      ],
      "correct": 1,
      "difficulty": "medium"
    },
    {
      "q": "In tort law, which type of damages is awarded to punish a defendant and deter future misconduct rather than to compensate the plaintiff?",
      "choices": [
        "Compensatory damages",
        "Nominal damages",
        "Punitive damages",
        "Liquidated damages"
      ],
      "correct": 2,
      "difficulty": "medium"
    },
    {
      "q": "What does the Latin phrase 'amicus curiae' literally translate to in English legal practice?",
      "choices": [
        "Friend of the court",
        "Duty to the client",
        "Duty of good faith",
        "Against the law"
      ],
      "correct": 0,
      "difficulty": "medium"
    },
    {
      "q": "In property law, which type of ownership interest allows one party to use and enjoy property during another person's lifetime?",
      "choices": [
        "Fee simple",
        "Life estate",
        "Leasehold",
        "Easement"
      ],
      "correct": 1,
      "difficulty": "medium"
    },
    {
      "q": "What is the principle in common law that requires courts to follow precedent established by earlier decisions in similar cases?",
      "choices": [
        "Res judicata",
        "Stare decisis",
        "Habeas corpus",
        "Pro bono publico"
      ],
      "correct": 1,
      "difficulty": "medium"
    },
    {
      "q": "Which U.S. Supreme Court case established that state executives may not indefinitely detain persons without judicial review?",
      "choices": [
        "Gideon v. Wainwright",
        "Boumediene v. Bush",
        "Brown v. Board of Education",
        "Miranda v. Arizona"
      ],
      "correct": 1,
      "difficulty": "medium"
    },
    {
      "q": "In family law, what term describes the legal dissolution of a marriage?",
      "choices": [
        "Annulment",
        "Divorce",
        "Separation",
        "Dissolution of partnership"
      ],
      "correct": 1,
      "difficulty": "medium"
    },
    {
      "q": "What legal concept protects individuals from self-incrimination by allowing them to remain silent during criminal proceedings?",
      "choices": [
        "Right to counsel",
        "Right against self-incrimination",
        "Right to confront witnesses",
        "Right to bail"
      ],
      "correct": 1,
      "difficulty": "medium"
    },
    {
      "q": "In trust law, what fiduciary duty requires a trustee to act in the best interests of the beneficiary?",
      "choices": [
        "Duty of loyalty",
        "Duty of care",
        "Duty of disclosure",
        "Duty of impartiality"
      ],
      "correct": 0,
      "difficulty": "medium"
    },
    {
      "q": "Which legal principle establishes that a matter already judged in court cannot be tried again between the same parties?",
      "choices": [
        "Stare decisis",
        "Res judicata",
        "Collateral estoppel",
        "Equitable estoppel"
      ],
      "correct": 1,
      "difficulty": "medium"
    },
    {
      "q": "What term describes a defendant's written response to a plaintiff's complaint in civil litigation?",
      "choices": [
        "Petition",
        "Answer",
        "Demurrer",
        "Motion to dismiss"
      ],
      "correct": 1,
      "difficulty": "medium"
    },
    {
      "q": "In intellectual property law, what type of protection grants an inventor exclusive rights to an invention for a set period?",
      "choices": [
        "Trademark",
        "Copyright",
        "Patent",
        "Trade secret"
      ],
      "correct": 2,
      "difficulty": "medium"
    },
    {
      "q": "Which doctrine in tort law holds that an owner of land may be liable for injuries caused by artificial conditions on the property?",
      "choices": [
        "Negligence per se",
        "Premises liability",
        "Strict liability",
        "Assumption of risk"
      ],
      "correct": 1,
      "difficulty": "medium"
    },
    {
      "q": "What is the primary purpose of a subpoena in legal proceedings?",
      "choices": [
        "To file a counterclaim",
        "To compel testimony or production of evidence",
        "To request a continuance",
        "To appeal a judgment"
      ],
      "correct": 1,
      "difficulty": "medium"
    },
    {
      "q": "In contract law, what term describes a circumstance that excuses performance when unforeseen events make performance impossible?",
      "choices": [
        "Breach of contract",
        "Anticipatory repudiation",
        "Impossibility of performance",
        "Material breach"
      ],
      "correct": 2,
      "difficulty": "medium"
    },
    {
      "q": "Which legal principle requires that governmental actions must have a legitimate purpose and use rational means to achieve it?",
      "choices": [
        "Strict scrutiny",
        "Intermediate scrutiny",
        "Rational basis review",
        "De novo review"
      ],
      "correct": 2,
      "difficulty": "medium"
    },
    {
      "q": "What term describes evidence that is excluded because it was obtained in violation of a defendant's constitutional rights?",
      "choices": [
        "Hearsay",
        "Inadmissible evidence",
        "Fruit of the poisonous tree",
        "Character evidence"
      ],
      "correct": 2,
      "difficulty": "medium"
    },
    {
      "q": "In administrative law, what term describes a formal proceeding where an agency hears evidence before making a decision?",
      "choices": [
        "Judicial review",
        "Administrative hearing",
        "Rulemaking",
        "Licensing"
      ],
      "correct": 1,
      "difficulty": "medium"
    },
    {
      "q": "In H.L.A. Hart's legal theory, what are the two types of rules that form the foundation of a legal system?",
      "choices": [
        "Statutory rules and common law rules",
        "Primary rules and secondary rules",
        "Constitutional rules and procedural rules",
        "Substantive rules and evidentiary rules"
      ],
      "correct": 1,
      "difficulty": "medium"
    },
    {
      "q": "Which landmark U.S. Supreme Court case established the principle of judicial review in 1803?",
      "choices": [
        "McCulloch v. Maryland",
        "Marbury v. Madison",
        "Gibbons v. Ogden",
        "Fletcher v. Peck"
      ],
      "correct": 1,
      "difficulty": "medium"
    },
    {
      "q": "What is the legal term for the person or party who initiates a civil lawsuit?",
      "choices": [
        "Defendant",
        "Appellant",
        "Plaintiff",
        "Respondent"
      ],
      "correct": 2,
      "difficulty": "medium"
    },
    {
      "q": "In the 2014 case Riley v. California, the U.S. Supreme Court primarily addressed what legal issue?",
      "choices": [
        "Fourth Amendment protections for digital data on mobile devices",
        "First Amendment rights in social media",
        "Due process in electronic surveillance",
        "Fifth Amendment self-incrimination in digital communications"
      ],
      "correct": 0,
      "difficulty": "medium"
    },
    {
      "q": "Which legal scholar defined law as 'the command of a sovereign, backed by the threat of a sanction'?",
      "choices": [
        "William Blackstone",
        "John Austin",
        "Ronald Dworkin",
        "Hans Kelsen"
      ],
      "correct": 1,
      "difficulty": "medium"
    },
    {
      "q": "The Magna Carta, sealed by King John in 1215, primarily established what legal principle?",
      "choices": [
        "Divine right of monarchy",
        "Limits on royal power and protection of certain rights",
        "Abolition of feudalism",
        "Universal suffrage"
      ],
      "correct": 1,
      "difficulty": "medium"
    },
    {
      "q": "Which U.S. Supreme Court case established that criminal defendants have a constitutional right to an attorney?",
      "choices": [
        "Miranda v. Arizona",
        "Powell v. Alabama",
        "Gideon v. Wainwright",
        "In re Gault"
      ],
      "correct": 2,
      "difficulty": "medium"
    },
    {
      "q": "What is the primary focus of analytic jurisprudence as a field of legal study?",
      "choices": [
        "How laws should be applied to specific cases",
        "What law is and its fundamental nature",
        "Historical development of legal systems",
        "Economic efficiency of legal rules"
      ],
      "correct": 1,
      "difficulty": "medium"
    },
    {
      "q": "The internment of Japanese Americans upheld in Korematsu v. United States (1944) occurred during which historical period?",
      "choices": [
        "The Great Depression",
        "World War II",
        "The Korean War",
        "The Vietnam War"
      ],
      "correct": 1,
      "difficulty": "medium"
    },
    {
      "q": "Which English legal scholar wrote the influential 'Commentaries on the Laws of England' in the 18th century?",
      "choices": [
        "Edward Coke",
        "William Blackstone",
        "Glanville Williams",
        "Jeremy Bentham"
      ],
      "correct": 1,
      "difficulty": "medium"
    },
    {
      "q": "In Donoghue v. Stevenson (1932), the House of Lords established what fundamental principle of tort law?",
      "choices": [
        "Strict liability for defective products",
        "A manufacturer owes a duty of care to consumers",
        "Negligence requires direct contractual privity",
        "Product warranties are absolute"
      ],
      "correct": 1,
      "difficulty": "medium"
    },
    {
      "q": "The Code of Hammurabi, developed around 1750 BCE in Babylon, is significant in legal history for what reason?",
      "choices": [
        "It was the first written legal code",
        "It established democratic governance",
        "It abolished slavery throughout the world",
        "It introduced trial by jury"
      ],
      "correct": 0,
      "difficulty": "medium"
    },
    {
      "q": "Which constitutional amendment to the U.S. Constitution protects freedom of speech and religion?",
      "choices": [
        "First Amendment",
        "Fifth Amendment",
        "Tenth Amendment",
        "Fourteenth Amendment"
      ],
      "correct": 0,
      "difficulty": "medium"
    },
    {
      "q": "Who appoints justices to the U.S. Supreme Court?",
      "choices": [
        "The U.S. Congress",
        "The President of the United States",
        "State governors collectively",
        "The Chief Justice"
      ],
      "correct": 1,
      "difficulty": "medium"
    },
    {
      "q": "What title is held by the head of the U.S. Supreme Court?",
      "choices": [
        "President of the Supreme Court",
        "Senior Justice",
        "Chief Justice",
        "Lord Chief Judge"
      ],
      "correct": 2,
      "difficulty": "medium"
    },
    {
      "q": "The phenomenon of legal systems adopting laws and institutions from other jurisdictions is known as what?",
      "choices": [
        "Legal harmonization",
        "Legal transplantation",
        "Comparative jurisprudence",
        "Institutional borrowing"
      ],
      "correct": 1,
      "difficulty": "medium"
    },
    {
      "q": "Which branch of jurisprudence addresses the question 'what should law be?' rather than 'what is law?'",
      "choices": [
        "Analytic jurisprudence",
        "Historical jurisprudence",
        "Normative jurisprudence",
        "Sociological jurisprudence"
      ],
      "correct": 2,
      "difficulty": "medium"
    },
    {
      "q": "In the medieval University of Bologna, which scholar is credited with rediscovering and systematizing Roman law?",
      "choices": [
        "Irnerius",
        "Accursius",
        "Bartolus",
        "Azo"
      ],
      "correct": 0,
      "difficulty": "medium"
    },
    {
      "q": "What professional degree must a lawyer typically complete before being admitted to practice law in the United States?",
      "choices": [
        "Bachelor of Laws (LL.B.)",
        "Doctor of Jurisprudence (D.J.)",
        "Juris Doctor (J.D.)",
        "Legal Doctorate (L.D.)"
      ],
      "correct": 2,
      "difficulty": "medium"
    },
    {
      "q": "In contract law, what term describes a promise made by one party in exchange for consideration from another party?",
      "choices": [
        "Offer",
        "Acceptance",
        "Covenant",
        "Estoppel"
      ],
      "correct": 0,
      "difficulty": "medium"
    },
    {
      "q": "Which legal principle holds that a person cannot be punished for conduct that was legal at the time it was committed?",
      "choices": [
        "Ex post facto prohibition",
        "Habeas corpus",
        "Double jeopardy",
        "Due process"
      ],
      "correct": 0,
      "difficulty": "medium"
    },
    {
      "q": "What is the legal term for the obligation one party owes to another to exercise reasonable care to avoid causing harm?",
      "choices": [
        "Negligence",
        "Duty of care",
        "Breach",
        "Proximate cause"
      ],
      "correct": 1,
      "difficulty": "medium"
    },
    {
      "q": "In the 1960s landmark case establishing that defendants must be informed of their rights before police questioning, which case created the foundation for modern Miranda warnings?",
      "choices": [
        "Gideon v. Wainwright",
        "Mapp v. Ohio",
        "Miranda v. Arizona",
        "Escobedo v. Illinois"
      ],
      "correct": 2,
      "difficulty": "medium"
    },
    {
      "q": "What legal doctrine allows courts to overturn or modify their own previous decisions when circumstances or understanding has significantly changed?",
      "choices": [
        "Stare decisis",
        "Overruling",
        "Distinguishing",
        "Remanding"
      ],
      "correct": 1,
      "difficulty": "medium"
    },
    {
      "q": "Which 2013 Supreme Court decision struck down a key provision of the Voting Rights Act of 1965?",
      "choices": [
        "Shelby County v. Holder",
        "Bush v. Gore",
        "Voting Rights Act Cases",
        "Fifteenth Amendment Cases"
      ],
      "correct": 0,
      "difficulty": "medium"
    },
    {
      "q": "In property law, what term describes a legal interest in land or property that belongs to the person and is inheritable?",
      "choices": [
        "Fee simple",
        "Lease",
        "Easement",
        "Covenant"
      ],
      "correct": 0,
      "difficulty": "medium"
    },
    {
      "q": "What legal principle, derived from Roman law, states that agreements must be kept and performed in good faith?",
      "choices": [
        "Caveat emptor",
        "Pacta sunt servanda",
        "Res judicata",
        "Amicus curiae"
      ],
      "correct": 1,
      "difficulty": "medium"
    },
    {
      "q": "In a civil lawsuit, what is the standard of proof required for a plaintiff to prevail against a defendant?",
      "choices": [
        "Beyond a reasonable doubt",
        "Clear and convincing evidence",
        "Preponderance of the evidence",
        "Probable cause"
      ],
      "correct": 2,
      "difficulty": "medium"
    },
    {
      "q": "Which legal concept refers to the wrongful act or omission that causes injury and forms the basis of a tort claim?",
      "choices": [
        "Damages",
        "Breach of duty",
        "Liability",
        "Injury"
      ],
      "correct": 1,
      "difficulty": "medium"
    },
    {
      "q": "What term describes a court's authority to hear and decide a particular case based on geography, subject matter, or parties involved?",
      "choices": [
        "Venue",
        "Jurisdiction",
        "Procedure",
        "Adjudication"
      ],
      "correct": 1,
      "difficulty": "medium"
    }
  ]
}