{
  "slug": "nickelodeon-trivia",
  "name": "Nickelodeon",
  "description": "SpongeBob, slime, Rugrats, iCarly, and 40+ years of Nick.",
  "processedAt": "2026-05-09T00:00:00Z",
  "status": "pilot",
  "questions": [
    {
      "q": "What's the name of Nickelodeon's iconic spongy fast-food cook who lives in a pineapple under the sea?",
      "choices": [
        "SpongeBob SquarePants",
        "Patrick Star",
        "Sandy Cheeks",
        "Squidward"
      ],
      "correct": 0,
      "category": "Nickelodeon",
      "difficulty": "easy",
      "source": {
        "original_a": "SpongeBob SquarePants",
        "verified": true,
        "notes": "Premiered May 1, 1999."
      }
    },
    {
      "q": "Who voices SpongeBob SquarePants?",
      "choices": [
        "Tom Kenny",
        "Bill Fagerbakke",
        "Rodger Bumpass",
        "Doug Lawrence"
      ],
      "correct": 0,
      "category": "Nickelodeon",
      "difficulty": "medium",
      "source": {
        "original_a": "Tom Kenny",
        "verified": true,
        "notes": "Has voiced SpongeBob since 1999."
      }
    },
    {
      "q": "What underwater town is SpongeBob SquarePants set in?",
      "choices": [
        "Bikini Bottom",
        "Tide City",
        "Coral Bay",
        "Ocean Town"
      ],
      "correct": 0,
      "category": "Nickelodeon",
      "difficulty": "easy",
      "source": {
        "original_a": "Nickelodeon",
        "verified": true,
        "notes": "Located beneath the real Bikini Atoll."
      }
    },
    {
      "q": "What's the iconic fast-food restaurant where SpongeBob fries patties?",
      "choices": [
        "The Krusty Krab",
        "The Chum Bucket",
        "Krabs Burger",
        "Goofy Goober"
      ],
      "correct": 0,
      "category": "Nickelodeon",
      "difficulty": "easy",
      "source": {
        "original_a": "Nickelodeon",
        "verified": true,
        "notes": "Owned by Eugene H. Krabs."
      }
    },
    {
      "q": "What was Nickelodeon's iconic slime gag known as?",
      "choices": [
        "Getting slimed",
        "Goo bath",
        "Slime drop",
        "Splat shower"
      ],
      "correct": 0,
      "category": "Nickelodeon",
      "difficulty": "easy",
      "source": {
        "original_a": "Nickelodeon",
        "verified": true,
        "notes": "Originated on the Canadian show 'You Can't Do That on Television' in 1981."
      }
    },
    {
      "q": "Which Nickelodeon kids' game show featured kids running through obstacle courses to win prizes?",
      "choices": [
        "Double Dare",
        "Legends of the Hidden Temple",
        "Figure It Out",
        "GUTS"
      ],
      "correct": 0,
      "category": "Nickelodeon",
      "difficulty": "medium",
      "source": {
        "original_a": "Nickelodeon",
        "verified": true,
        "notes": "Hosted by Marc Summers, premiered 1986."
      }
    },
    {
      "q": "What animated show follows Tommy Pickles and a group of toddlers?",
      "choices": [
        "Rugrats",
        "Doug",
        "The Wild Thornberrys",
        "Hey Arnold!"
      ],
      "correct": 0,
      "category": "Nickelodeon",
      "difficulty": "easy",
      "source": {
        "original_a": "Nickelodeon",
        "verified": true,
        "notes": "Premiered 1991."
      }
    },
    {
      "q": "What 90s Nick show is about a football-headed kid living in a New York boarding house?",
      "choices": [
        "Hey Arnold!",
        "Doug",
        "The Adventures of Pete & Pete",
        "KaBlam!"
      ],
      "correct": 0,
      "category": "Nickelodeon",
      "difficulty": "medium",
      "source": {
        "original_a": "Nickelodeon",
        "verified": true,
        "notes": "Premiered 1996."
      }
    },
    {
      "q": "Which Avatar series aired on Nickelodeon from 2005-2008?",
      "choices": [
        "Avatar: The Last Airbender",
        "The Legend of Korra",
        "Avatar: The Way of Water",
        "Avatar Chronicles"
      ],
      "correct": 0,
      "category": "Nickelodeon",
      "difficulty": "easy",
      "source": {
        "original_a": "Nickelodeon",
        "verified": true,
        "notes": "Sequel 'Korra' aired 2012-2014."
      }
    },
    {
      "q": "What live-action sketch comedy show launched the careers of Amanda Bynes and Kenan Thompson?",
      "choices": [
        "All That",
        "The Amanda Show",
        "Kenan & Kel",
        "Drake & Josh"
      ],
      "correct": 0,
      "category": "Nickelodeon",
      "difficulty": "medium",
      "source": {
        "original_a": "Nickelodeon",
        "verified": true,
        "notes": "Premiered 1994. Sketch-based show in the SNL vein."
      }
    },
    {
      "q": "Which 2007-2012 Nickelodeon show starred Miranda Cosgrove making web shows?",
      "choices": ["iCarly", "Victorious", "Drake & Josh", "Zoey 101"],
      "correct": 0,
      "category": "Nickelodeon",
      "difficulty": "easy",
      "source": {
        "original_a": "Nickelodeon",
        "verified": true,
        "notes": "Revived in 2021 on Paramount+."
      }
    },
    {
      "q": "Who created Nickelodeon's 'Drake & Josh' and 'iCarly'?",
      "choices": [
        "Dan Schneider",
        "Steve Hillenburg",
        "Steven Spielberg",
        "Joe Murray"
      ],
      "correct": 0,
      "category": "Nickelodeon",
      "difficulty": "hard",
      "source": {
        "original_a": "Nickelodeon",
        "verified": true,
        "notes": ""
      }
    },
    {
      "q": "What 1999 SpongeBob film franchise launched a series of theatrical movies?",
      "choices": [
        "The SpongeBob SquarePants Movie (2004)",
        "SpongeBob Goes Hollywood",
        "SpongeBob: The First",
        "SpongeBob Origins"
      ],
      "correct": 0,
      "category": "Nickelodeon",
      "difficulty": "medium",
      "source": {
        "original_a": "Nickelodeon",
        "verified": true,
        "notes": ""
      }
    },
    {
      "q": "What 90s sketch show featured Big Pete and Little Pete (both named Pete)?",
      "choices": [
        "The Adventures of Pete & Pete",
        "All That",
        "Salute Your Shorts",
        "Hey Dude"
      ],
      "correct": 0,
      "category": "Nickelodeon",
      "difficulty": "medium",
      "source": {
        "original_a": "Nickelodeon",
        "verified": true,
        "notes": ""
      }
    },
    {
      "q": "What 2013 mid-credits scene revealed in Avatar: The Legend of Korra Book 4?",
      "choices": [
        "Korra and Asami's relationship was confirmed in finale (no mid-credits)",
        "There was no Korra finale",
        "Aang appears",
        "Ozai returns"
      ],
      "correct": 0,
      "category": "Nickelodeon",
      "difficulty": "hard",
      "source": {
        "original_a": "Nickelodeon",
        "verified": true,
        "notes": "Korra and Asami walking into the spirit world together — landmark LGBTQ+ representation in animation."
      }
    },
    {
      "q": "What was the FIRST show ever broadcast on Nickelodeon (1979)?",
      "choices": [
        "Pinwheel",
        "You Can't Do That on Television",
        "The Mysterious Cities of Gold",
        "Belle and Sebastian"
      ],
      "correct": 0,
      "category": "Nickelodeon",
      "difficulty": "hard",
      "source": {
        "original_a": "Pinwheel",
        "verified": true,
        "notes": "Pinwheel premiered April 1, 1979 — Nick's launch day."
      }
    },
    {
      "q": "What was the original logo of Nickelodeon shaped like?",
      "choices": [
        "A splat / orange blob",
        "A star",
        "A square",
        "A diamond"
      ],
      "correct": 0,
      "category": "Nickelodeon",
      "difficulty": "medium",
      "source": {
        "original_a": "Nickelodeon",
        "verified": true,
        "notes": "Used 1984-2009. Replaced 2009 with simple orange wordmark; the splat returned in 2023."
      }
    },
    {
      "q": "What show featured a martial-arts-trained sponge-and-friend duo trying to retrieve King Neptune's crown?",
      "choices": [
        "The SpongeBob SquarePants Movie (2004)",
        "Sponge Out of Water",
        "Sponge on the Run",
        "Mermaid Man"
      ],
      "correct": 0,
      "category": "Nickelodeon",
      "difficulty": "medium",
      "source": {
        "original_a": "Nickelodeon",
        "verified": true,
        "notes": ""
      }
    },
    {
      "q": "What 1990s Nickelodeon cartoon featured a girl named Eliza who could talk to animals?",
      "choices": [
        "The Wild Thornberrys",
        "Aaahh!!! Real Monsters",
        "Rocko's Modern Life",
        "Doug"
      ],
      "correct": 0,
      "category": "Nickelodeon",
      "difficulty": "hard",
      "source": {
        "original_a": "The Wild Thornberrys",
        "verified": true,
        "notes": "audit-corrected 2026-05-09: removed inaccurate 'gross-out cartoon with talking food' framing; Eliza Thornberry talks to animals, not food."
      }
    },
    {
      "q": "What live-action Nick sitcom (2004-2007) starred Drake Bell and Josh Peck as stepbrothers?",
      "choices": [
        "Drake & Josh",
        "Zoey 101",
        "Ned's Declassified School Survival Guide",
        "All That"
      ],
      "correct": 0,
      "category": "Nickelodeon",
      "difficulty": "easy",
      "source": {
        "original_a": "Drake & Josh",
        "verified": true,
        "notes": "audit-corrected 2026-05-09: was incorrectly described as a 2002-2007 'teen detective show'. Drake & Josh is a buddy/teen sitcom about stepbrothers, premiered Jan 2004."
      }
    }
  ]
}
